<?xml version = '1.0' encoding = 'UTF-8'?>
<Relation class="oracle.dbtools.crest.model.design.logical.Relation" name="profe_prestamo" directorySegmentName="seg_0" id="B6F419CC-A80A-8E06-F473-F1580946E115">
<createdBy>CC6</createdBy>
<createdTime>2022-03-04 14:11:51 UTC</createdTime>
<ownerDesignName>Examen unidad II</ownerDesignName>
<engineerTo>
<item key="587D3F4B-FC8D-C873-AB72-5A6B74C40828" value="true"/>
</engineerTo>
<sourcePk>858120AA-8EBA-9219-BE37-66E9D008DA3D</sourcePk>
<identifying>false</identifying>
<optionalSource>false</optionalSource>
<optionalTarget>true</optionalTarget>
<sourceCardinality>1</sourceCardinality>
<sourceEntity>9EF63A54-79C2-1F82-790D-9433F2C39391</sourceEntity>
<targetCardinalityString>*</targetCardinalityString>
<targetEntity>95343A4D-CED4-FC39-5E4F-84F14D5D22EB</targetEntity>
<transferable>true</transferable>
<deleteRule>NO ACTION</deleteRule>
</Relation>